scrapelab/__init__.py
scrapelab-0.0.6.dist-info/LICENCE
scrapelab-0.0.6.dist-info/METADATA
scrapelab-0.0.6.dist-info/WHEEL
scrapelab-0.0.6.dist-info/top_level.txt
scrapelab-0.0.6.dist-info/RECORD
