Metadata-Version: 2.1
Name: scrapelab
Version: 0.0.6
Summary: A small example package
Home-page: https://github.com/romio20l/scrape_lab
Author: romio20l
Author-email: romio20l@hotmail.com
License: UNKNOWN
Platform: UNKNOWN
Classifier: Programming Language :: Python :: 3
Classifier: License :: OSI Approved :: MIT License
Classifier: Operating System :: OS Independent
Requires-Python: >=3.6
Requires-Dist: scrapy
